{
  "context": {
    "date": "2021-02-26T09:34:00+00:00",
    "host_name": "fv-az63-770",
    "executable": "/home/runner/work/CppLinq/CppLinq/build/main",
    "num_cpus": 2,
    "mhz_per_cpu": 2295,
    "cpu_scaling_enabled": false,
    "caches": [
      {
        "type": "Data",
        "level": 1,
        "size": 32768,
        "num_sharing": 1
      },
      {
        "type": "Instruction",
        "level": 1,
        "size": 32768,
        "num_sharing": 1
      },
      {
        "type": "Unified",
        "level": 2,
        "size": 262144,
        "num_sharing": 1
      },
      {
        "type": "Unified",
        "level": 3,
        "size": 52428800,
        "num_sharing": 2
      }
    ],
    "load_avg": [1.17,0.54,0.21],
    "library_build_type": "release"
  },
  "benchmarks": [
    {
      "name": "NativeAggregate",
      "run_name": "NativeAggregate",
      "run_type": "iteration",
      "repetitions": 0,
      "repetition_index": 0,
      "threads": 1,
      "iterations": 12039049,
      "real_time": 5.3449157736628209e+01,
      "cpu_time": 5.3442969706328135e+01,
      "time_unit": "ns",
      "Alloc Cnt": 0.0000000000000000e+00,
      "Alloc Memory": 0.0000000000000000e+00
    },
    {
      "name": "MyLinqAggregate",
      "run_name": "MyLinqAggregate",
      "run_type": "iteration",
      "repetitions": 0,
      "repetition_index": 0,
      "threads": 1,
      "iterations": 13442325,
      "real_time": 5.6151364142736945e+01,
      "cpu_time": 5.6147659277691915e+01,
      "time_unit": "ns",
      "Alloc Cnt": 0.0000000000000000e+00,
      "Alloc Memory": 0.0000000000000000e+00
    },
    {
      "name": "CppLinqAggregate",
      "run_name": "CppLinqAggregate",
      "run_type": "iteration",
      "repetitions": 0,
      "repetition_index": 0,
      "threads": 1,
      "iterations": 11638960,
      "real_time": 5.6504957143936402e+01,
      "cpu_time": 5.6502912459532475e+01,
      "time_unit": "ns",
      "Alloc Cnt": 0.0000000000000000e+00,
      "Alloc Memory": 0.0000000000000000e+00
    },
    {
      "name": "NativeAll",
      "run_name": "NativeAll",
      "run_type": "iteration",
      "repetitions": 0,
      "repetition_index": 0,
      "threads": 1,
      "iterations": 3457552,
      "real_time": 2.0433412454823750e+02,
      "cpu_time": 2.0433050956283523e+02,
      "time_unit": "ns",
      "Alloc Cnt": 0.0000000000000000e+00,
      "Alloc Memory": 0.0000000000000000e+00
    },
    {
      "name": "MyLinqAll",
      "run_name": "MyLinqAll",
      "run_type": "iteration",
      "repetitions": 0,
      "repetition_index": 0,
      "threads": 1,
      "iterations": 3456949,
      "real_time": 1.9779199779921285e+02,
      "cpu_time": 1.9778852681945847e+02,
      "time_unit": "ns",
      "Alloc Cnt": 0.0000000000000000e+00,
      "Alloc Memory": 0.0000000000000000e+00
    },
    {
      "name": "CppLinqAll",
      "run_name": "CppLinqAll",
      "run_type": "iteration",
      "repetitions": 0,
      "repetition_index": 0,
      "threads": 1,
      "iterations": 2352280,
      "real_time": 2.9112333438195458e+02,
      "cpu_time": 2.9105790892240736e+02,
      "time_unit": "ns",
      "Alloc Cnt": 0.0000000000000000e+00,
      "Alloc Memory": 0.0000000000000000e+00
    },
    {
      "name": "NativeAny",
      "run_name": "NativeAny",
      "run_type": "iteration",
      "repetitions": 0,
      "repetition_index": 0,
      "threads": 1,
      "iterations": 12590442,
      "real_time": 6.1760782584123632e+01,
      "cpu_time": 6.1754293455305231e+01,
      "time_unit": "ns",
      "Alloc Cnt": 0.0000000000000000e+00,
      "Alloc Memory": 0.0000000000000000e+00
    },
    {
      "name": "MyLinqAny",
      "run_name": "MyLinqAny",
      "run_type": "iteration",
      "repetitions": 0,
      "repetition_index": 0,
      "threads": 1,
      "iterations": 12700755,
      "real_time": 6.5059303876027471e+01,
      "cpu_time": 6.5054335588711041e+01,
      "time_unit": "ns",
      "Alloc Cnt": 0.0000000000000000e+00,
      "Alloc Memory": 0.0000000000000000e+00
    },
    {
      "name": "CppLinqAny",
      "run_name": "CppLinqAny",
      "run_type": "iteration",
      "repetitions": 0,
      "repetition_index": 0,
      "threads": 1,
      "iterations": 11639888,
      "real_time": 5.7399975583957449e+01,
      "cpu_time": 5.7397217825463599e+01,
      "time_unit": "ns",
      "Alloc Cnt": 0.0000000000000000e+00,
      "Alloc Memory": 0.0000000000000000e+00
    },
    {
      "name": "NativeAvg",
      "run_name": "NativeAvg",
      "run_type": "iteration",
      "repetitions": 0,
      "repetition_index": 0,
      "threads": 1,
      "iterations": 66727,
      "real_time": 1.1176660602155271e+04,
      "cpu_time": 1.1175632562530913e+04,
      "time_unit": "ns",
      "Alloc Cnt": 0.0000000000000000e+00,
      "Alloc Memory": 0.0000000000000000e+00
    },
    {
      "name": "MyLinqAvg",
      "run_name": "MyLinqAvg",
      "run_type": "iteration",
      "repetitions": 0,
      "repetition_index": 0,
      "threads": 1,
      "iterations": 60152,
      "real_time": 1.1548660111052246e+04,
      "cpu_time": 1.1548467233009702e+04,
      "time_unit": "ns",
      "Alloc Cnt": 0.0000000000000000e+00,
      "Alloc Memory": 0.0000000000000000e+00
    },
    {
      "name": "CppLinqAvg",
      "run_name": "CppLinqAvg",
      "run_type": "iteration",
      "repetitions": 0,
      "repetition_index": 0,
      "threads": 1,
      "iterations": 138976,
      "real_time": 4.8722692551230439e+03,
      "cpu_time": 4.8720282135044954e+03,
      "time_unit": "ns",
      "Alloc Cnt": 0.0000000000000000e+00,
      "Alloc Memory": 0.0000000000000000e+00
    },
    {
      "name": "NativeContains",
      "run_name": "NativeContains",
      "run_type": "iteration",
      "repetitions": 0,
      "repetition_index": 0,
      "threads": 1,
      "iterations": 268533,
      "real_time": 2.6231558430435643e+03,
      "cpu_time": 2.6230221574257148e+03,
      "time_unit": "ns",
      "Alloc Cnt": 0.0000000000000000e+00,
      "Alloc Memory": 0.0000000000000000e+00
    },
    {
      "name": "MyLinqContains",
      "run_name": "MyLinqContains",
      "run_type": "iteration",
      "repetitions": 0,
      "repetition_index": 0,
      "threads": 1,
      "iterations": 135880,
      "real_time": 5.2607698999116683e+03,
      "cpu_time": 5.2598654327347667e+03,
      "time_unit": "ns",
      "Alloc Cnt": 0.0000000000000000e+00,
      "Alloc Memory": 0.0000000000000000e+00
    },
    {
      "name": "CppLinqContains",
      "run_name": "CppLinqContains",
      "run_type": "iteration",
      "repetitions": 0,
      "repetition_index": 0,
      "threads": 1,
      "iterations": 113467,
      "real_time": 6.4192985008856404e+03,
      "cpu_time": 6.4185802391884836e+03,
      "time_unit": "ns",
      "Alloc Cnt": 0.0000000000000000e+00,
      "Alloc Memory": 0.0000000000000000e+00
    },
    {
      "name": "NativeCount",
      "run_name": "NativeCount",
      "run_type": "iteration",
      "repetitions": 0,
      "repetition_index": 0,
      "threads": 1,
      "iterations": 12090136,
      "real_time": 5.8529271961870208e+01,
      "cpu_time": 5.8523837862535281e+01,
      "time_unit": "ns",
      "Alloc Cnt": 0.0000000000000000e+00,
      "Alloc Memory": 0.0000000000000000e+00
    },
    {
      "name": "MyLinqCount",
      "run_name": "MyLinqCount",
      "run_type": "iteration",
      "repetitions": 0,
      "repetition_index": 0,
      "threads": 1,
      "iterations": 10396038,
      "real_time": 5.6303408952525309e+01,
      "cpu_time": 5.6271242948515649e+01,
      "time_unit": "ns",
      "Alloc Cnt": 0.0000000000000000e+00,
      "Alloc Memory": 0.0000000000000000e+00
    },
    {
      "name": "CppLinqCount",
      "run_name": "CppLinqCount",
      "run_type": "iteration",
      "repetitions": 0,
      "repetition_index": 0,
      "threads": 1,
      "iterations": 12157476,
      "real_time": 5.6557326948453735e+01,
      "cpu_time": 5.6554152029582546e+01,
      "time_unit": "ns",
      "Alloc Cnt": 0.0000000000000000e+00,
      "Alloc Memory": 0.0000000000000000e+00
    },
    {
      "name": "NativeDistinct",
      "run_name": "NativeDistinct",
      "run_type": "iteration",
      "repetitions": 0,
      "repetition_index": 0,
      "threads": 1,
      "iterations": 344,
      "real_time": 2.0019949011628001e+06,
      "cpu_time": 1.9976387994186028e+06,
      "time_unit": "ns",
      "Alloc Cnt": 4.3110000000000000e+03,
      "Alloc Memory": 6.2064000000000000e+05
    },
    {
      "name": "MyLinqDistinct",
      "run_name": "MyLinqDistinct",
      "run_type": "iteration",
      "repetitions": 0,
      "repetition_index": 0,
      "threads": 1,
      "iterations": 1330,
      "real_time": 5.2558988947369799e+05,
      "cpu_time": 5.2555643157894688e+05,
      "time_unit": "ns",
      "Alloc Cnt": 4.3120000000000000e+03,
      "Alloc Memory": 5.9938400000000000e+05
    },
    {
      "name": "CppLinqDistinct",
      "run_name": "CppLinqDistinct",
      "run_type": "iteration",
      "repetitions": 0,
      "repetition_index": 0,
      "threads": 1,
      "iterations": 342,
      "real_time": 2.0125939941520458e+06,
      "cpu_time": 2.0123583187134478e+06,
      "time_unit": "ns",
      "Alloc Cnt": 4.3200000000000000e+03,
      "Alloc Memory": 1.2958880000000000e+06
    },
    {
      "name": "NativeEmpty",
      "run_name": "NativeEmpty",
      "run_type": "iteration",
      "repetitions": 0,
      "repetition_index": 0,
      "threads": 1,
      "iterations": 13065811,
      "real_time": 5.8823902932623312e+01,
      "cpu_time": 5.8822157920392534e+01,
      "time_unit": "ns",
      "Alloc Cnt": 0.0000000000000000e+00,
      "Alloc Memory": 0.0000000000000000e+00
    },
    {
      "name": "MyLinqEmpty",
      "run_name": "MyLinqEmpty",
      "run_type": "iteration",
      "repetitions": 0,
      "repetition_index": 0,
      "threads": 1,
      "iterations": 13738897,
      "real_time": 5.8127091134025605e+01,
      "cpu_time": 5.8123524617733210e+01,
      "time_unit": "ns",
      "Alloc Cnt": 0.0000000000000000e+00,
      "Alloc Memory": 0.0000000000000000e+00
    },
    {
      "name": "CppLinqEmpty",
      "run_name": "CppLinqEmpty",
      "run_type": "iteration",
      "repetitions": 0,
      "repetition_index": 0,
      "threads": 1,
      "iterations": 9745605,
      "real_time": 7.1185283007056782e+01,
      "cpu_time": 7.0627779804332206e+01,
      "time_unit": "ns",
      "Alloc Cnt": 1.0000000000000000e+00,
      "Alloc Memory": 6.4000000000000000e+01
    },
    {
      "name": "NativeSelect",
      "run_name": "NativeSelect",
      "run_type": "iteration",
      "repetitions": 0,
      "repetition_index": 0,
      "threads": 1,
      "iterations": 7217,
      "real_time": 9.8030867119300310e+04,
      "cpu_time": 9.8022221005958185e+04,
      "time_unit": "ns",
      "Alloc Cnt": 1.0000000000000000e+00,
      "Alloc Memory": 3.2000000000000000e+05
    },
    {
      "name": "MyLinqSelect",
      "run_name": "MyLinqSelect",
      "run_type": "iteration",
      "repetitions": 0,
      "repetition_index": 0,
      "threads": 1,
      "iterations": 4782,
      "real_time": 1.3570941844416596e+05,
      "cpu_time": 1.3569839774153082e+05,
      "time_unit": "ns",
      "Alloc Cnt": 1.0000000000000000e+00,
      "Alloc Memory": 3.2000000000000000e+05
    },
    {
      "name": "CppLinqSelect",
      "run_name": "CppLinqSelect",
      "run_type": "iteration",
      "repetitions": 0,
      "repetition_index": 0,
      "threads": 1,
      "iterations": 2267,
      "real_time": 2.9498101146889629e+05,
      "cpu_time": 2.9494307543008332e+05,
      "time_unit": "ns",
      "Alloc Cnt": 1.1000000000000000e+01,
      "Alloc Memory": 1.0480640000000000e+06
    },
    {
      "name": "NativeWhere",
      "run_name": "NativeWhere",
      "run_type": "iteration",
      "repetitions": 0,
      "repetition_index": 0,
      "threads": 1,
      "iterations": 1094,
      "real_time": 6.8266764716635726e+05,
      "cpu_time": 6.8264251096892171e+05,
      "time_unit": "ns",
      "Alloc Cnt": 0.0000000000000000e+00,
      "Alloc Memory": 0.0000000000000000e+00
    },
    {
      "name": "MyLinqWhere",
      "run_name": "MyLinqWhere",
      "run_type": "iteration",
      "repetitions": 0,
      "repetition_index": 0,
      "threads": 1,
      "iterations": 5623,
      "real_time": 1.3364385701583192e+05,
      "cpu_time": 1.3363957104748365e+05,
      "time_unit": "ns",
      "Alloc Cnt": 1.0000000000000000e+00,
      "Alloc Memory": 5.4891200000000000e+05
    },
    {
      "name": "CppLinqWhere",
      "run_name": "CppLinqWhere",
      "run_type": "iteration",
      "repetitions": 0,
      "repetition_index": 0,
      "threads": 1,
      "iterations": 1033,
      "real_time": 6.9786194385286793e+05,
      "cpu_time": 6.9776687996127945e+05,
      "time_unit": "ns",
      "Alloc Cnt": 1.0000000000000000e+00,
      "Alloc Memory": 8.9600000000000000e+02
    },
    {
      "name": "NativeSelectMany",
      "run_name": "NativeSelectMany",
      "run_type": "iteration",
      "repetitions": 0,
      "repetition_index": 0,
      "threads": 1,
      "iterations": 6252,
      "real_time": 1.1226283989123219e+05,
      "cpu_time": 1.1225401103646828e+05,
      "time_unit": "ns",
      "Alloc Cnt": 1.4000000000000000e+01,
      "Alloc Memory": 3.1650800000000000e+05
    },
    {
      "name": "NativeSelectMany",
      "run_name": "NativeSelectMany",
      "run_type": "iteration",
      "repetitions": 0,
      "repetition_index": 0,
      "threads": 1,
      "iterations": 6299,
      "real_time": 1.0774685807271086e+05,
      "cpu_time": 1.0773838085410383e+05,
      "time_unit": "ns",
      "Alloc Cnt": 1.4000000000000000e+01,
      "Alloc Memory": 3.1650800000000000e+05
    },
    {
      "name": "MyLinqSelectMany",
      "run_name": "MyLinqSelectMany",
      "run_type": "iteration",
      "repetitions": 0,
      "repetition_index": 0,
      "threads": 1,
      "iterations": 6432,
      "real_time": 1.0379607462686727e+05,
      "cpu_time": 1.0379113059701507e+05,
      "time_unit": "ns",
      "Alloc Cnt": 1.4000000000000000e+01,
      "Alloc Memory": 3.1650800000000000e+05
    },
    {
      "name": "NativeDistinct",
      "run_name": "NativeDistinct",
      "run_type": "iteration",
      "repetitions": 0,
      "repetition_index": 0,
      "threads": 1,
      "iterations": 43,
      "real_time": 1.6505297209302526e+07,
      "cpu_time": 1.6504871604651179e+07,
      "time_unit": "ns",
      "Alloc Cnt": 0.0000000000000000e+00,
      "Alloc Memory": 0.0000000000000000e+00
    },
    {
      "name": "MyLinqDistinct",
      "run_name": "MyLinqDistinct",
      "run_type": "iteration",
      "repetitions": 0,
      "repetition_index": 0,
      "threads": 1,
      "iterations": 1000,
      "real_time": 5.2727032100000314e+05,
      "cpu_time": 5.2726322199999844e+05,
      "time_unit": "ns",
      "Alloc Cnt": 4.3120000000000000e+03,
      "Alloc Memory": 5.9938400000000000e+05
    },
    {
      "name": "CppLinqDistinct",
      "run_name": "CppLinqDistinct",
      "run_type": "iteration",
      "repetitions": 0,
      "repetition_index": 0,
      "threads": 1,
      "iterations": 397,
      "real_time": 1.8167779596977870e+06,
      "cpu_time": 1.8166893022669966e+06,
      "time_unit": "ns",
      "Alloc Cnt": 4.3110000000000000e+03,
      "Alloc Memory": 3.8017600000000000e+05
    },
    {
      "name": "MyLinqOrderBy",
      "run_name": "MyLinqOrderBy",
      "run_type": "iteration",
      "repetitions": 0,
      "repetition_index": 0,
      "threads": 1,
      "iterations": 437,
      "real_time": 1.5685178649885315e+06,
      "cpu_time": 1.5683380091533116e+06,
      "time_unit": "ns",
      "Alloc Cnt": 1.0000000000000000e+00,
      "Alloc Memory": 5.6000000000000000e+05
    },
    {
      "name": "CppLinqOrderBy",
      "run_name": "CppLinqOrderBy",
      "run_type": "iteration",
      "repetitions": 0,
      "repetition_index": 0,
      "threads": 1,
      "iterations": 284,
      "real_time": 2.5269924119718275e+06,
      "cpu_time": 2.5267667183098588e+06,
      "time_unit": "ns",
      "Alloc Cnt": 1.0000000000000000e+00,
      "Alloc Memory": 8.9600000000000000e+02
    },
    {
      "name": "NativeFirstOrDefault",
      "run_name": "NativeFirstOrDefault",
      "run_type": "iteration",
      "repetitions": 0,
      "repetition_index": 0,
      "threads": 1,
      "iterations": 38045,
      "real_time": 1.9014507872256665e+04,
      "cpu_time": 1.9012996530424425e+04,
      "time_unit": "ns",
      "Alloc Cnt": 0.0000000000000000e+00,
      "Alloc Memory": 0.0000000000000000e+00
    },
    {
      "name": "MyLinqFirstOrDefault",
      "run_name": "MyLinqFirstOrDefault",
      "run_type": "iteration",
      "repetitions": 0,
      "repetition_index": 0,
      "threads": 1,
      "iterations": 38355,
      "real_time": 1.9035999478555412e+04,
      "cpu_time": 1.9034432590275093e+04,
      "time_unit": "ns",
      "Alloc Cnt": 0.0000000000000000e+00,
      "Alloc Memory": 0.0000000000000000e+00
    },
    {
      "name": "CppLinqFirstOrDefault",
      "run_name": "CppLinqFirstOrDefault",
      "run_type": "iteration",
      "repetitions": 0,
      "repetition_index": 0,
      "threads": 1,
      "iterations": 36295,
      "real_time": 1.9000570684667258e+04,
      "cpu_time": 1.8998427083620481e+04,
      "time_unit": "ns",
      "Alloc Cnt": 0.0000000000000000e+00,
      "Alloc Memory": 0.0000000000000000e+00
    }
  ]
}
